pytentacle/__init__.py
pytentacle/async_client.py
pytentacle/auth.py
pytentacle/client.py
pytentacle/exceptions.py
pytentacle/py.typed
pytentacle/types.py
pytentacle/api/__init__.py
pytentacle/api/electricity.py
pytentacle/api/gas.py
pytentacle/api/industry.py
pytentacle/api/products.py
pytentacle/core/__init__.py
pytentacle/core/async_base.py
pytentacle/core/base.py
pytentacle/models/__init__.py
pytentacle/models/common.py
pytentacle/models/consumption.py
pytentacle/models/meter_points.py
pytentacle/models/products.py
pytentacle/models/tariffs.py
pytentacle-0.1.1.dist-info/METADATA
pytentacle-0.1.1.dist-info/WHEEL
pytentacle-0.1.1.dist-info/licenses/LICENSE
pytentacle-0.1.1.dist-info/RECORD
